flask_and_kafka/__init__.py
flask_and_kafka/close.py
flask_and_kafka/consumer.py
flask_and_kafka/formatters.py
flask_and_kafka/log.py
flask_and_kafka/producer.py
flask_and_kafka-0.0.4.dist-info/LICENSE
flask_and_kafka-0.0.4.dist-info/METADATA
flask_and_kafka-0.0.4.dist-info/WHEEL
flask_and_kafka-0.0.4.dist-info/top_level.txt
flask_and_kafka-0.0.4.dist-info/RECORD
