Metadata-Version: 2.1
Name: flask-and-kafka
Version: 0.0.4
Summary: Easily write your kafka producers and consumers in flask
Home-page: https://github.com/heysaeid/flask-and-kafka.git
Author: Saeid Noormohammadi
Author-email: heysaeid92@gmail.com
License: MIT
Keywords: flask,kafka,flask kafka,flask kafka consumer,flask-kafka,flask-kafka-consumer,flask-and-kafka,Flask-And-Kafka,flask kafka producer,kafka producer,flask-kafka-producer
Platform: any
Classifier: Framework :: Flask
Classifier: Intended Audience :: Developers
Classifier: License :: OSI Approved :: MIT License
Classifier: Operating System :: OS Independent
Classifier: Programming Language :: Python
Classifier: Programming Language :: Python :: 3.6
Classifier: Programming Language :: Python :: 3.7
Classifier: Programming Language :: Python :: 3.8
Classifier: Programming Language :: Python :: 3.9
Classifier: Topic :: Software Development :: Libraries :: Python Modules
License-File: LICENSE
Requires-Dist: confluent-kafka
Requires-Dist: flask
